{
"meta":{"test_sets":[],"test_metrics":[],"learn_metrics":[{"best_value":"Min","name":"Logloss"}],"launch_mode":"Train","parameters":"","iteration_count":150,"learn_sets":["learn"],"name":"experiment"},
"iterations":[
{"learn":[0.6358530965],"iteration":0,"passed_time":0.1437365134,"remaining_time":21.41674049},
{"learn":[0.5893776938],"iteration":1,"passed_time":0.1542121588,"remaining_time":11.41169975},
{"learn":[0.5497426942],"iteration":2,"passed_time":0.1593752322,"remaining_time":7.809386376},
{"learn":[0.5188972182],"iteration":3,"passed_time":0.1659032243,"remaining_time":6.055467686},
{"learn":[0.4935967022],"iteration":4,"passed_time":0.1697448881,"remaining_time":4.922601756},
{"learn":[0.4706620991],"iteration":5,"passed_time":0.173134714,"remaining_time":4.155233137},
{"learn":[0.4538549475],"iteration":6,"passed_time":0.1767419745,"remaining_time":3.61058605},
{"learn":[0.4397881239],"iteration":7,"passed_time":0.1823490086,"remaining_time":3.236694902},
{"learn":[0.4268692803],"iteration":8,"passed_time":0.1876415765,"remaining_time":2.939718032},
{"learn":[0.4156419518],"iteration":9,"passed_time":0.191178688,"remaining_time":2.676501632},
{"learn":[0.405504756],"iteration":10,"passed_time":0.1984451258,"remaining_time":2.507624771},
{"learn":[0.3958602634],"iteration":11,"passed_time":0.2029763839,"remaining_time":2.334228415},
{"learn":[0.3892574117],"iteration":12,"passed_time":0.2076746717,"remaining_time":2.18857154},
{"learn":[0.3833355072],"iteration":13,"passed_time":0.2114789515,"remaining_time":2.054366958},
{"learn":[0.3776958756],"iteration":14,"passed_time":0.2219702307,"remaining_time":1.997732076},
{"learn":[0.3732808737],"iteration":15,"passed_time":0.2450716995,"remaining_time":2.052475484},
{"learn":[0.3705054241],"iteration":16,"passed_time":0.2496094782,"remaining_time":1.952827094},
{"learn":[0.3668206013],"iteration":17,"passed_time":0.2873790688,"remaining_time":2.107446505},
{"learn":[0.363629546],"iteration":18,"passed_time":0.2963404648,"remaining_time":2.043189521},
{"learn":[0.3602555001],"iteration":19,"passed_time":0.3017176011,"remaining_time":1.961164407},
{"learn":[0.3566654069],"iteration":20,"passed_time":0.3075660333,"remaining_time":1.889334205},
{"learn":[0.3536227108],"iteration":21,"passed_time":0.3282445337,"remaining_time":1.909786378},
{"learn":[0.3513608495],"iteration":22,"passed_time":0.3337297175,"remaining_time":1.84276844},
{"learn":[0.34980508],"iteration":23,"passed_time":0.338437814,"remaining_time":1.776798524},
{"learn":[0.3481889943],"iteration":24,"passed_time":0.3434631389,"remaining_time":1.717315695},
{"learn":[0.3477049619],"iteration":25,"passed_time":0.3463204462,"remaining_time":1.651682128},
{"learn":[0.3464831741],"iteration":26,"passed_time":0.3513969392,"remaining_time":1.600808279},
{"learn":[0.3444734832],"iteration":27,"passed_time":0.368066292,"remaining_time":1.603717415},
{"learn":[0.3433551467],"iteration":28,"passed_time":0.3915905346,"remaining_time":1.633877748},
{"learn":[0.3417578544],"iteration":29,"passed_time":0.4012549482,"remaining_time":1.605019793},
{"learn":[0.3407909513],"iteration":30,"passed_time":0.4252483755,"remaining_time":1.632405054},
{"learn":[0.3398413877],"iteration":31,"passed_time":0.4424593543,"remaining_time":1.631568869},
{"learn":[0.3387931382],"iteration":32,"passed_time":0.4510727935,"remaining_time":1.599258086},
{"learn":[0.3376550774],"iteration":33,"passed_time":0.4799137057,"remaining_time":1.637352643},
{"learn":[0.337059599],"iteration":34,"passed_time":0.4913143219,"remaining_time":1.614318486},
{"learn":[0.3358317714],"iteration":35,"passed_time":0.5246075634,"remaining_time":1.661257284},
{"learn":[0.3353735654],"iteration":36,"passed_time":0.5431101028,"remaining_time":1.658687611},
{"learn":[0.3343702909],"iteration":37,"passed_time":0.5946516027,"remaining_time":1.752657355},
{"learn":[0.3339732679],"iteration":38,"passed_time":0.6223401456,"remaining_time":1.771275799},
{"learn":[0.3333097008],"iteration":39,"passed_time":0.6331176948,"remaining_time":1.741073661},
{"learn":[0.3324313534],"iteration":40,"passed_time":0.6491855339,"remaining_time":1.725883493},
{"learn":[0.3313855238],"iteration":41,"passed_time":0.6655193543,"remaining_time":1.711335483},
{"learn":[0.3302445002],"iteration":42,"passed_time":0.6768434117,"remaining_time":1.684238257},
{"learn":[0.3296844279],"iteration":43,"passed_time":0.6816143601,"remaining_time":1.642070959},
{"learn":[0.3293201183],"iteration":44,"passed_time":0.6857778125,"remaining_time":1.600148229},
{"learn":[0.3288217199],"iteration":45,"passed_time":0.6905438363,"remaining_time":1.561229543},
{"learn":[0.3277253767],"iteration":46,"passed_time":0.6958968781,"remaining_time":1.525050605},
{"learn":[0.3271908174],"iteration":47,"passed_time":0.700959932,"remaining_time":1.489539855},
{"learn":[0.3264639079],"iteration":48,"passed_time":0.7092389598,"remaining_time":1.461900713},
{"learn":[0.3259353843],"iteration":49,"passed_time":0.7142206561,"remaining_time":1.428441312},
{"learn":[0.324951124],"iteration":50,"passed_time":0.7205557934,"remaining_time":1.398725952},
{"learn":[0.3238505258],"iteration":51,"passed_time":0.7315914025,"remaining_time":1.378768412},
{"learn":[0.3231703741],"iteration":52,"passed_time":0.7381527507,"remaining_time":1.350958808},
{"learn":[0.3225788049],"iteration":53,"passed_time":0.742937031,"remaining_time":1.320776944},
{"learn":[0.3221848078],"iteration":54,"passed_time":0.7473558869,"remaining_time":1.290887441},
{"learn":[0.3216023473],"iteration":55,"passed_time":0.7509772174,"remaining_time":1.260568901},
{"learn":[0.321248257],"iteration":56,"passed_time":0.7554449031,"remaining_time":1.232568},
{"learn":[0.3207209519],"iteration":57,"passed_time":0.7602632217,"remaining_time":1.205934765},
{"learn":[0.3202490985],"iteration":58,"passed_time":0.7663948397,"remaining_time":1.182066617},
{"learn":[0.3199530994],"iteration":59,"passed_time":0.7719122969,"remaining_time":1.157868445},
{"learn":[0.3191118937],"iteration":60,"passed_time":0.7761790973,"remaining_time":1.132458027},
{"learn":[0.3187109907],"iteration":61,"passed_time":0.7803248536,"remaining_time":1.107557857},
{"learn":[0.3180511631],"iteration":62,"passed_time":0.7852104626,"remaining_time":1.084338258},
{"learn":[0.3176712966],"iteration":63,"passed_time":0.7890479615,"remaining_time":1.060283198},
{"learn":[0.3171938696],"iteration":64,"passed_time":0.7932387664,"remaining_time":1.037312233},
{"learn":[0.3167321718],"iteration":65,"passed_time":0.7966543653,"remaining_time":1.013923738},
{"learn":[0.3164689591],"iteration":66,"passed_time":0.8017386896,"remaining_time":0.9931986751},
{"learn":[0.3156718325],"iteration":67,"passed_time":0.8057567707,"remaining_time":0.9716478706},
{"learn":[0.3153040732],"iteration":68,"passed_time":0.8095975493,"remaining_time":0.9503971231},
{"learn":[0.3150205908],"iteration":69,"passed_time":0.8145039917,"remaining_time":0.9308617048},
{"learn":[0.3145088933],"iteration":70,"passed_time":0.8191956095,"remaining_time":0.9114993401},
{"learn":[0.313912467],"iteration":71,"passed_time":0.8239814721,"remaining_time":0.8926465948},
{"learn":[0.3134208532],"iteration":72,"passed_time":0.8298495636,"remaining_time":0.8753207726},
{"learn":[0.3125138076],"iteration":73,"passed_time":0.8385230527,"remaining_time":0.8611858379},
{"learn":[0.312178014],"iteration":74,"passed_time":0.8419988855,"remaining_time":0.8419988855},
{"learn":[0.3115231203],"iteration":75,"passed_time":0.8463100029,"remaining_time":0.824038687},
{"learn":[0.3110415664],"iteration":76,"passed_time":0.8508534239,"remaining_time":0.806653246},
{"learn":[0.3107735975],"iteration":77,"passed_time":0.8546213947,"remaining_time":0.7888812874},
{"learn":[0.3104482773],"iteration":78,"passed_time":0.8575974422,"remaining_time":0.7707521316},
{"learn":[0.3095760934],"iteration":79,"passed_time":0.8617441945,"remaining_time":0.7540261702},
{"learn":[0.3092603866],"iteration":80,"passed_time":0.8658547484,"remaining_time":0.7375799709},
{"learn":[0.3087128606],"iteration":81,"passed_time":0.8691007638,"remaining_time":0.7207177066},
{"learn":[0.308124551],"iteration":82,"passed_time":0.8733742543,"remaining_time":0.7050129523},
{"learn":[0.307533844],"iteration":83,"passed_time":0.8766953583,"remaining_time":0.6888320673},
{"learn":[0.3072455989],"iteration":84,"passed_time":0.8816159283,"remaining_time":0.6741768863},
{"learn":[0.3068714961],"iteration":85,"passed_time":0.8858996817,"remaining_time":0.6592741817},
{"learn":[0.3062646177],"iteration":86,"passed_time":0.8981003441,"remaining_time":0.650348525},
{"learn":[0.305771428],"iteration":87,"passed_time":0.9072735897,"remaining_time":0.6392154837},
{"learn":[0.3052468005],"iteration":88,"passed_time":0.9113932813,"remaining_time":0.6246628108},
{"learn":[0.3047956014],"iteration":89,"passed_time":0.9181128803,"remaining_time":0.6120752535},
{"learn":[0.3044777148],"iteration":90,"passed_time":0.9216902215,"remaining_time":0.5975793744},
{"learn":[0.3041593926],"iteration":91,"passed_time":0.9271366731,"remaining_time":0.584499207},
{"learn":[0.3036293017],"iteration":92,"passed_time":0.9309405922,"remaining_time":0.570576492},
{"learn":[0.3032199926],"iteration":93,"passed_time":0.9344142994,"remaining_time":0.5566723486},
{"learn":[0.3027404723],"iteration":94,"passed_time":0.9380124869,"remaining_time":0.5430598608},
{"learn":[0.3022714608],"iteration":95,"passed_time":0.9441308742,"remaining_time":0.5310736167},
{"learn":[0.3017271927],"iteration":96,"passed_time":0.947375691,"remaining_time":0.5176382642},
{"learn":[0.301368372],"iteration":97,"passed_time":0.9511044482,"remaining_time":0.5046676664},
{"learn":[0.3009706722],"iteration":98,"passed_time":0.9540468138,"remaining_time":0.4914786617},
{"learn":[0.3006766216],"iteration":99,"passed_time":0.956926774,"remaining_time":0.478463387},
{"learn":[0.3002150442],"iteration":100,"passed_time":0.9607420497,"remaining_time":0.4661025786},
{"learn":[0.2999009272],"iteration":101,"passed_time":0.9650491832,"remaining_time":0.4541407921},
{"learn":[0.2996051931],"iteration":102,"passed_time":0.9698566251,"remaining_time":0.4425559357},
{"learn":[0.2992392379],"iteration":103,"passed_time":0.9752853491,"remaining_time":0.4313762121},
{"learn":[0.2989715543],"iteration":104,"passed_time":0.9838758149,"remaining_time":0.4216610635},
{"learn":[0.2987035213],"iteration":105,"passed_time":0.9873410111,"remaining_time":0.409839665},
{"learn":[0.2984911086],"iteration":106,"passed_time":0.9934408874,"remaining_time":0.3992332538},
{"learn":[0.2980140347],"iteration":107,"passed_time":1.001691417,"remaining_time":0.3895466623},
{"learn":[0.297717555],"iteration":108,"passed_time":1.011274853,"remaining_time":0.3803877887},
{"learn":[0.2972769167],"iteration":109,"passed_time":1.014770674,"remaining_time":0.3690075178},
{"learn":[0.2968745074],"iteration":110,"passed_time":1.017802533,"remaining_time":0.3576062954},
{"learn":[0.2963517965],"iteration":111,"passed_time":1.021986427,"remaining_time":0.3467453947},
{"learn":[0.2960322736],"iteration":112,"passed_time":1.025712266,"remaining_time":0.3358526889},
{"learn":[0.2957648597],"iteration":113,"passed_time":1.032592026,"remaining_time":0.3260816924},
{"learn":[0.2954197039],"iteration":114,"passed_time":1.035745998,"remaining_time":0.315227043},
{"learn":[0.2951841195],"iteration":115,"passed_time":1.039822781,"remaining_time":0.3047756428},
{"learn":[0.2948595051],"iteration":116,"passed_time":1.043778459,"remaining_time":0.2943990524},
{"learn":[0.2942945449],"iteration":117,"passed_time":1.04677383,"remaining_time":0.2838708693},
{"learn":[0.2940730824],"iteration":118,"passed_time":1.050415476,"remaining_time":0.2736376449},
{"learn":[0.2935945545],"iteration":119,"passed_time":1.053938612,"remaining_time":0.263484653},
{"learn":[0.2933913891],"iteration":120,"passed_time":1.058852451,"remaining_time":0.2537745545},
{"learn":[0.2930500429],"iteration":121,"passed_time":1.06266113,"remaining_time":0.2438894398},
{"learn":[0.2929048998],"iteration":122,"passed_time":1.065395364,"remaining_time":0.2338672751},
{"learn":[0.2928347095],"iteration":123,"passed_time":1.06811752,"remaining_time":0.2239601252},
{"learn":[0.2923952524],"iteration":124,"passed_time":1.071725452,"remaining_time":0.2143450904},
{"learn":[0.2921857869],"iteration":125,"passed_time":1.074434782,"remaining_time":0.2046542443},
{"learn":[0.292122283],"iteration":126,"passed_time":1.077080921,"remaining_time":0.1950618991},
{"learn":[0.2917337965],"iteration":127,"passed_time":1.080530926,"remaining_time":0.185716253},
{"learn":[0.2915265847],"iteration":128,"passed_time":1.08338447,"remaining_time":0.1763649137},
{"learn":[0.2911918584],"iteration":129,"passed_time":1.087080739,"remaining_time":0.1672431906},
{"learn":[0.2909602065],"iteration":130,"passed_time":1.090513362,"remaining_time":0.1581660601},
{"learn":[0.2907527065],"iteration":131,"passed_time":1.09291089,"remaining_time":0.1490333032},
{"learn":[0.290487238],"iteration":132,"passed_time":1.095272886,"remaining_time":0.1399972862},
{"learn":[0.290252991],"iteration":133,"passed_time":1.097942214,"remaining_time":0.1310975778},
{"learn":[0.2900344212],"iteration":134,"passed_time":1.101237999,"remaining_time":0.1223597777},
{"learn":[0.2896736181],"iteration":135,"passed_time":1.105780262,"remaining_time":0.1138303211},
{"learn":[0.289421893],"iteration":136,"passed_time":1.108209742,"remaining_time":0.1051585887},
{"learn":[0.289050907],"iteration":137,"passed_time":1.111105788,"remaining_time":0.09661789457},
{"learn":[0.288906065],"iteration":138,"passed_time":1.113372019,"remaining_time":0.08810857708},
{"learn":[0.2884025551],"iteration":139,"passed_time":1.11656576,"remaining_time":0.07975469716},
{"learn":[0.2879974454],"iteration":140,"passed_time":1.120407446,"remaining_time":0.07151536887},
{"learn":[0.2877419292],"iteration":141,"passed_time":1.122722116,"remaining_time":0.06325195022},
{"learn":[0.2872748569],"iteration":142,"passed_time":1.125043719,"remaining_time":0.05507207015},
{"learn":[0.287073243],"iteration":143,"passed_time":1.1275567,"remaining_time":0.04698152915},
{"learn":[0.2866850491],"iteration":144,"passed_time":1.130116763,"remaining_time":0.03896954354},
{"learn":[0.2863092865],"iteration":145,"passed_time":1.132568174,"remaining_time":0.03102926505},
{"learn":[0.2860947788],"iteration":146,"passed_time":1.135690872,"remaining_time":0.02317736474},
{"learn":[0.2858150337],"iteration":147,"passed_time":1.138532573,"remaining_time":0.01538557531},
{"learn":[0.2857002234],"iteration":148,"passed_time":1.142505462,"remaining_time":0.007667821892},
{"learn":[0.2853718387],"iteration":149,"passed_time":1.145244258,"remaining_time":0}
]}passed_time":1.084278896,"remaining_time":0}
]}ion":149,"passed_time":0.9065582483,"remaining_time":0}
]}